[
 {
  "taskId": "test-3574336689",
  "points": 1,
  "results": [
   {
    "code": 0,
    "output": "Well done!",
    "timestamp": 1570100888921,
    "state": "pass"
   }
  ]
 },
 {
  "taskId": "test-2277622674",
  "points": 1,
  "results": [
   {
    "code": 0,
    "output": "Well done!",
    "timestamp": 1570100944838,
    "state": "pass"
   }
  ]
 },
 {
  "taskId": "test-4074605942",
  "points": 1,
  "results": [
   {
    "code": 0,
    "output": "Well done!",
    "timestamp": 1570114810026,
    "state": "pass"
   },
   {
    "code": 1,
    "output": "You are missing some tasks.\nRequested statements: 3\nWritten statements: 4\nEach statement must end with a semicolon.",
    "timestamp": 1570100964070,
    "state": "fail"
   }
  ]
 },
 {
  "taskId": "test-3027502085",
  "points": 1,
  "results": [
   {
    "code": 0,
    "output": "Well done!",
    "timestamp": 1570101013871,
    "state": "pass"
   }
  ]
 },
 {
  "taskId": "test-480230319",
  "points": 1,
  "results": [
   {
    "code": 0,
    "output": "Well done!",
    "timestamp": 1570101032467,
    "state": "pass"
   }
  ]
 },
 {
  "taskId": "test-3965937864",
  "points": 1,
  "results": [
   {
    "code": 0,
    "output": "Well done!",
    "timestamp": 1570101089461,
    "state": "pass"
   }
  ]
 },
 {
  "taskId": "test-1820944031",
  "points": 1,
  "results": [
   {
    "code": 0,
    "output": "Well done!",
    "timestamp": 1570101102706,
    "state": "pass"
   }
  ]
 },
 {
  "taskId": "test-3292589540",
  "points": 1,
  "results": [
   {
    "code": 0,
    "output": "Well done!",
    "timestamp": 1570101113972,
    "state": "pass"
   }
  ]
 }
]